pypairtree/__init__.py
pypairtree/pairtree.py
pypairtree/pairtreelist.py
pypairtree-1.1.0.dist-info/METADATA
pypairtree-1.1.0.dist-info/RECORD
pypairtree-1.1.0.dist-info/WHEEL
pypairtree-1.1.0.dist-info/top_level.txt
