Metadata-Version: 2.1
Name: pypairtree
Version: 1.1.0
Summary: Python implementation of Pairtree for storing objects in a filesystem hierarchy that maps object identifiers to two character directory paths
Home-page: https://github.com/unt-libraries/pypairtree
Author: University of North Texas Libraries
Author-email: lauren.ko@unt.edu
License: LICENSE.txt
Keywords: python pairtree
Platform: UNKNOWN
Classifier: Intended Audience :: Developers
Classifier: Intended Audience :: System Administrators
Classifier: Natural Language :: English
Classifier: Programming Language :: Python
Classifier: Programming Language :: Python :: 2
Classifier: Programming Language :: Python :: 2.7
Classifier: Programming Language :: Python :: 3
Classifier: Programming Language :: Python :: 3.4
Classifier: Programming Language :: Python :: 3.5
Classifier: Programming Language :: Python :: 3.6
